nosa_autostreamlit/__init__.py
nosa_autostreamlit/cli.py
nosa_autostreamlit/core/__init__.py
nosa_autostreamlit/generators/__init__.py
nosa_autostreamlit/generators/base_generator.py
nosa_autostreamlit/generators/data_visualization_generator.py
nosa_autostreamlit/generators/machine_learning_generator.py
nosa_autostreamlit/utils/__init__.py
nosa_autostreamlit/utils/data_utils.py
nosa_autostreamlit-0.1.2.dist-info/LICENSE
nosa_autostreamlit-0.1.2.dist-info/METADATA
nosa_autostreamlit-0.1.2.dist-info/WHEEL
nosa_autostreamlit-0.1.2.dist-info/top_level.txt
nosa_autostreamlit-0.1.2.dist-info/RECORD
