Metadata-Version: 2.1
Name: nosa-autostreamlit
Version: 0.1.2
Summary: Automated Machine Learning and Data Visualization Framework
Home-page: https://github.com/thesnak/nosa-autostreamlit
Author: Mohamed Mahmoud
Author-email: Mohamed Mahmoud <mohamed.mahmoud0726@gmail.com>
License: MIT License
Project-URL: Homepage, https://github.com/thesnak/nosa-autostreamlit
Project-URL: Repository, https://github.com/thesnak/nosa-autostreamlit
Keywords: machine-learning,data-visualization,streamlit
Classifier: Development Status :: 3 - Alpha
Classifier: Intended Audience :: Developers
Classifier: License :: OSI Approved :: MIT License
Classifier: Programming Language :: Python :: 3.8
Classifier: Programming Language :: Python :: 3.9
Classifier: Programming Language :: Python :: 3.10
Requires-Python: >=3.8
License-File: LICENSE
Requires-Dist: streamlit
Requires-Dist: pandas
Requires-Dist: numpy
Requires-Dist: plotly
Requires-Dist: scikit-learn
Requires-Dist: joblib
Provides-Extra: dev
Requires-Dist: pytest; extra == "dev"
Requires-Dist: black; extra == "dev"
Requires-Dist: flake8; extra == "dev"
